silicon_analyser/grid.py
silicon_analyser/main.py
silicon_analyser/main_window.ui
silicon_analyser/mywindow.py
silicon_analyser/rect.py
silicon_analyser/savefiles.py
silicon_analyser/treeitem.py
silicon_analyser/dialogs/compute_stats.py
silicon_analyser/dialogs/compute_stats.ui
silicon_analyser/dialogs/pixel_image.py
silicon_analyser/dialogs/pixel_image.ui
silicon_analyser/helper/addgridbtn.py
silicon_analyser/helper/addlabelbtn.py
silicon_analyser/helper/ai.py
silicon_analyser/helper/autocomputebtn.py
silicon_analyser/helper/common.py
silicon_analyser/helper/computebtn.py
silicon_analyser/helper/fullimage.py
silicon_analyser/helper/minimap.py
silicon_analyser/helper/properties.py
silicon_analyser/helper/tree.py
silicon_analyser/helper/abstract/abstractcomputationmethod.py
silicon_analyser/helper/abstract/abstractimage.py
silicon_analyser/helper/abstract/abstractmywindow.py
silicon_analyser/helper/abstract/abstracttreehelper.py
silicon_analyser/helper/computation_methods/decision_tree.py
silicon_analyser/helper/computation_methods/neural_network.py
silicon_analyser-1.1.1.dist-info/LICENSE
silicon_analyser-1.1.1.dist-info/METADATA
silicon_analyser-1.1.1.dist-info/WHEEL
silicon_analyser-1.1.1.dist-info/entry_points.txt
silicon_analyser-1.1.1.dist-info/top_level.txt
silicon_analyser-1.1.1.dist-info/RECORD
