Metadata-Version: 2.1
Name: silicon-analyser
Version: 1.1.1
Summary: helps to analyse integrated circuit die images (for example from siliconpr0n.org) with the help of ai.
Author-email: CrazyT <crazyt2019+sa@gmail.com>
Project-URL: Homepage, https://github.com/TheCrazyT/SiliconAnalyser
Project-URL: Bug Tracker, https://github.com/TheCrazyT/SiliconAnalyser/issues
Classifier: Programming Language :: Python :: 3
Classifier: License :: OSI Approved :: MIT License
Classifier: Operating System :: OS Independent
Requires-Python: >=3.10
License-File: LICENSE
Requires-Dist: torch
Requires-Dist: numpy
Requires-Dist: pillow
Requires-Dist: keras
Requires-Dist: PyQt5
Requires-Dist: pyqtgraph
Requires-Dist: scikit-learn
Requires-Dist: packaging
